scikit_longitudinal/__init__.py
scikit_longitudinal/base.py
scikit_longitudinal/discovery.py
scikit_longitudinal/metrics.py
scikit_longitudinal/pipeline.py
scikit_longitudinal/data_preparation/__init__.py
scikit_longitudinal/data_preparation/aggregation_function.py
scikit_longitudinal/data_preparation/elsa_handler.py
scikit_longitudinal/data_preparation/longitudinal_dataset.py
scikit_longitudinal/data_preparation/merwav_time_minus.py
scikit_longitudinal/data_preparation/merwav_time_plus.py
scikit_longitudinal/data_preparation/separate_waves.py
scikit_longitudinal/estimators/__init__.py
scikit_longitudinal/estimators/ensemble/__init__.py
scikit_longitudinal/estimators/ensemble/lexicographical/__init__.py
scikit_longitudinal/estimators/ensemble/lexicographical/lexico_deep_forest.py
scikit_longitudinal/estimators/ensemble/lexicographical/lexico_gradient_boosting.py
scikit_longitudinal/estimators/ensemble/lexicographical/lexico_random_forest.py
scikit_longitudinal/estimators/ensemble/longitudinal_stacking/__init__.py
scikit_longitudinal/estimators/ensemble/longitudinal_stacking/longitudinal_stacking.py
scikit_longitudinal/estimators/ensemble/longitudinal_voting/__init__.py
scikit_longitudinal/estimators/ensemble/longitudinal_voting/custom_voting.py
scikit_longitudinal/estimators/ensemble/longitudinal_voting/longitudinal_voting.py
scikit_longitudinal/estimators/ensemble/nested_trees/__init__.py
scikit_longitudinal/estimators/ensemble/nested_trees/nested_trees.py
scikit_longitudinal/estimators/ensemble/nested_trees/utils.py
scikit_longitudinal/estimators/trees/__init__.py
scikit_longitudinal/estimators/trees/lexicographical/__init__.py
scikit_longitudinal/estimators/trees/lexicographical/lexico_decision_tree.py
scikit_longitudinal/estimators/trees/lexicographical/lexico_decision_tree_regressor.py
scikit_longitudinal/pipeline_managers/__init__.py
scikit_longitudinal/pipeline_managers/utils.py
scikit_longitudinal/pipeline_managers/manage_callbacks/__init__.py
scikit_longitudinal-0.1.5.dist-info/METADATA
scikit_longitudinal-0.1.5.dist-info/WHEEL
scikit_longitudinal-0.1.5.dist-info/top_level.txt
scikit_longitudinal-0.1.5.dist-info/RECORD
