Metadata-Version: 2.4
Name: Scikit-longitudinal
Version: 0.1.5
Summary: Scikit-longitudinal is an open-source Python library for longitudinal data analysis, building on Scikit-learn's foundation with tools tailored for repeated measures data.
Home-page: https://github.com/simonprovost/scikit-longitudinal
Author: Provost Simon, Alex Freitas
Author-email: Provost Simon <simon.gilbert.provost@gmail.com>, Alex Freitas <a.a.freitas@kent.ac.uk>
License: MIT
Project-URL: Homepage, https://github.com/simonprovost/scikit-longitudinal
Project-URL: Documentation, https://scikit-longitudinal.readthedocs.io/latest/
Project-URL: Releases, https://github.com/simonprovost/scikit-longitudinal/releases
Project-URL: Repository, https://github.com/simonprovost/scikit-longitudinal
Project-URL: Issues, https://github.com/simonprovost/scikit-longitudinal/issues/
Project-URL: Scientific Paper, https://joss.theoj.org/papers/10.21105/joss.08481
Classifier: License :: OSI Approved :: MIT License
Classifier: Programming Language :: Python :: 3
Requires-Python: >=3.9,<3.10
Requires-Dist: scipy>=1.5.0
Requires-Dist: pandas<2.0.0,>=1.5.3
Requires-Dist: matplotlib<4.0.0,>=3.7.0
Requires-Dist: jupyter<2.0.0,>=1.0.0
Requires-Dist: overrides<8.0.0,>=7.3.1
Requires-Dist: statsmodels<1.0.0,>=0.14.0
Requires-Dist: numpy==1.23.3
Requires-Dist: graphviz<1.0.0,>=0.20.1
Requires-Dist: liac-arff>=2.2.2
Requires-Dist: threadpoolctl<4.0.0,>=3.1.0
Requires-Dist: stopit>=1.1.2
Requires-Dist: rich>=13.6.0
Requires-Dist: joblib>=0.11
Requires-Dist: deep-forest>=0.1.7
Requires-Dist: scikit-lexicographical-trees==0.0.4
Requires-Dist: ray>=2.40.0
Dynamic: author
Dynamic: home-page
Dynamic: requires-python
